LICENSE.txt
MANIFEST.in
README.rst
TODO.rst
__init__.py
annotation.py
base.py
class_construct.py
close.py
disjoint.py
dl_render.py
driver.py
editor.py
entity.py
individual.py
instance_editor.py
instance_editor_qt.py
namespace.py
ntriples_diff.py
observe.py
owlready2_optimized.c
owlready2_optimized.pyx
owlxml_2_ntriples.py
prop.py
pyproject.toml
rdflib_store.py
rdfxml_2_ntriples.py
reasoning.py
rply.py
rule.py
setup.cfg
setup.py
setup_develop_mode.py
triplelite.py
triplelite_update.py
util.py
./LICENSE.txt
./README.rst
./__init__.py
./annotation.py
./base.py
./class_construct.py
./close.py
./disjoint.py
./dl_render.py
./driver.py
./editor.py
./entity.py
./individual.py
./instance_editor.py
./instance_editor_qt.py
./namespace.py
./ntriples_diff.py
./observe.py
./owlxml_2_ntriples.py
./prop.py
./rdflib_store.py
./rdfxml_2_ntriples.py
./reasoning.py
./rply.py
./rule.py
./setup_develop_mode.py
./triplelite.py
./triplelite_update.py
./util.py
./hermit/HermiT.jar
./hermit/Save.class
./hermit/Save.java
./hermit/readme.txt
./hermit/org/semanticweb/HermiT/Reasoner$1.class
./hermit/org/semanticweb/HermiT/Reasoner$10.class
./hermit/org/semanticweb/HermiT/Reasoner$11.class
./hermit/org/semanticweb/HermiT/Reasoner$2.class
./hermit/org/semanticweb/HermiT/Reasoner$3.class
./hermit/org/semanticweb/HermiT/Reasoner$4.class
./hermit/org/semanticweb/HermiT/Reasoner$5.class
./hermit/org/semanticweb/HermiT/Reasoner$6.class
./hermit/org/semanticweb/HermiT/Reasoner$7.class
./hermit/org/semanticweb/HermiT/Reasoner$8.class
./hermit/org/semanticweb/HermiT/Reasoner$9.class
./hermit/org/semanticweb/HermiT/Reasoner$OntologyChangeListener.class
./hermit/org/semanticweb/HermiT/Reasoner$ReasonerFactory.class
./hermit/org/semanticweb/HermiT/Reasoner.class
./hermit/org/semanticweb/HermiT/Reasoner.java
./hermit/org/semanticweb/HermiT/cli/Arg.class
./hermit/org/semanticweb/HermiT/cli/CommandLine$Action.class
./hermit/org/semanticweb/HermiT/cli/CommandLine$ClassifyAction.class
Owlready2.egg-info/dependency_links.txt
Owlready2.egg-info/top_level.txt
owlready2.egg-info/PKG-INFO
owlready2.egg-info/SOURCES.txt
owlready2.egg-info/dependency_links.txt
owlready2.egg-info/requires.txt
owlready2.egg-info/top_level.txt
